hippogym/__init__.py
hippogym/__main__.py
hippogym/agent.py
hippogym/bucketer.py
hippogym/communicator.py
hippogym/event_handler.py
hippogym/hippogym.py
hippogym/log.py
hippogym/message_handler.py
hippogym/recorder.py
hippogym/trial.py
hippogym/trialsteps/__init__.py
hippogym/trialsteps/gymstep.py
hippogym/trialsteps/trialstep.py
hippogym/ui_elements/__init__.py
hippogym/ui_elements/control_panel.py
hippogym/ui_elements/game_window.py
hippogym/ui_elements/grid.py
hippogym/ui_elements/info_panel.py
hippogym/ui_elements/text_box.py
hippogym/ui_elements/ui_element.py
hippogym/ui_elements/building_blocks/__init__.py
hippogym/ui_elements/building_blocks/button.py
hippogym/ui_elements/building_blocks/slider.py
hippogym-2.0.0a2.dist-info/LICENSE
hippogym-2.0.0a2.dist-info/METADATA
hippogym-2.0.0a2.dist-info/WHEEL
hippogym-2.0.0a2.dist-info/entry_points.txt
hippogym-2.0.0a2.dist-info/top_level.txt
hippogym-2.0.0a2.dist-info/RECORD
