Metadata-Version: 2.1
Name: hippogym
Version: 2.0.0a2
Author-email: Nick Nissen <nnissen@ualberta.ca>, Mathïs Fédérico <mathfederico@gmail.com>
License: Apache-2.0
Project-URL: Home-page, https://hippogym.irll.net
Project-URL: Source, https://github.com/IRLL/HIPPO_Gym
Project-URL: Documentation, https://hippogym.irll.net/
Keywords: gym,human,loop,reinforcement,learning
Requires-Python: >=3.8
License-File: LICENSE
Requires-Dist: gym (>=0.17.2)
Requires-Dist: atari-py (>=0.2.9)
Requires-Dist: shortuuid (>=1.0.1)
Requires-Dist: asyncio (>=3.4.3)
Requires-Dist: websockets (>=10.0)
Requires-Dist: numpy (>=1.20.0)
Requires-Dist: Pillow (>=9.0.1)
Requires-Dist: boto3 (>=1.14.20)
Requires-Dist: python-dotenv (>=0.14.0)
Requires-Dist: pyYaml (>=5.4)
Requires-Dist: pymitter
Provides-Extra: pyvis
Requires-Dist: pyvis ; extra == 'pyvis'
